maxgcp/__init__.py
maxgcp/_version.py
maxgcp/estimators.py
maxgcp/py.typed
maxgcp/summary.py
maxgcp/cli/__init__.py
maxgcp/cli/compare.py
maxgcp/cli/ldsc.py
maxgcp/cli/main.py
maxgcp/cli/utils.py
maxgcp/ldsc/__init__.py
maxgcp/ldsc/irwls.py
maxgcp/ldsc/jackknife.py
maxgcp/ldsc/ldscore.py
maxgcp/ldsc/parse.py
maxgcp/ldsc/regressions.py
maxgcp/ldsc/sumstats.py
maxgcp/ldsc/scripts/__init__.py
maxgcp/ldsc/scripts/ldsc.py
maxgcp/ldsc/scripts/make_annot.py
maxgcp/ldsc/scripts/munge_sumstats.py
maxgcp/ldsc/test/simulate.py
maxgcp/ldsc/test/test_irwls.py
maxgcp/ldsc/test/test_jackknife.py
maxgcp/ldsc/test/test_ldscore.py
maxgcp/ldsc/test/test_munge_sumstats.py
maxgcp/ldsc/test/test_parse.py
maxgcp/ldsc/test/test_regressions.py
maxgcp/ldsc/test/test_sumstats.py
maxgcp/ldsc/test/annot_test/test.annot
maxgcp/ldsc/test/annot_test/test1.frq
maxgcp/ldsc/test/munge_test/correct.sumstats
maxgcp/ldsc/test/munge_test/correct_merge.sumstats
maxgcp/ldsc/test/munge_test/merge_alleles
maxgcp/ldsc/test/munge_test/merge_alleles_bad
maxgcp/ldsc/test/munge_test/sumstats
maxgcp/ldsc/test/parse_test/test.cts
maxgcp/ldsc/test/parse_test/test.l2.M
maxgcp/ldsc/test/parse_test/test.l2.ldscore.gz
maxgcp/ldsc/test/parse_test/test.sumstats
maxgcp/ldsc/test/parse_test/test1.frq
maxgcp/ldsc/test/parse_test/test1.l2.M
maxgcp/ldsc/test/parse_test/test1.l2.ldscore.bz2
maxgcp/ldsc/test/parse_test/test2.frq.gz
maxgcp/ldsc/test/parse_test/test2.l2.M
maxgcp/ldsc/test/parse_test/test2.l2.ldscore.bz2
maxgcp/ldsc/test/parse_test/test_bad.l2.M
maxgcp/ldsc/test/plink_test/plink.bed
maxgcp/ldsc/test/plink_test/plink.bim
maxgcp/ldsc/test/plink_test/plink.fam
maxgcp/ldsc/test/plink_test/plink.map
maxgcp/ldsc/test/plink_test/plink.ped
maxgcp/ldsc/test/plink_test/test.annot
maxgcp/ldsc/test/reference_test/plink.bed
maxgcp/ldsc/test/reference_test/plink.bim
maxgcp/ldsc/test/reference_test/plink.fam
maxgcp/ldsc/test/reference_test/plink2.bim
maxgcp/ldsc/test/reference_test/test.N
maxgcp-0.1.5.dist-info/METADATA
maxgcp-0.1.5.dist-info/WHEEL
maxgcp-0.1.5.dist-info/entry_points.txt
maxgcp-0.1.5.dist-info/licenses/LICENSE
maxgcp-0.1.5.dist-info/RECORD
