Metadata-Version: 2.3
Name: maxgcp
Version: 0.1.5
Summary: Optimized phenotype definitions boost GWAS power
Project-URL: Repository, https://github.com/tatonetti-lab/maxgcp
Author-email: zietzm <michael.zietz@gmail.com>
License-File: LICENSE
Classifier: Development Status :: 3 - Alpha
Classifier: License :: OSI Approved :: MIT License
Classifier: Programming Language :: Python
Classifier: Programming Language :: Python :: 3 :: Only
Classifier: Programming Language :: Python :: 3.10
Classifier: Programming Language :: Python :: 3.11
Classifier: Programming Language :: Python :: 3.12
Requires-Python: >=3.10
Requires-Dist: bitarray>=2.9.2
Requires-Dist: igwas>=0.1.0
Requires-Dist: numpy>=1.26.4
Requires-Dist: pandas>=2.2.2
Requires-Dist: polars>=1.5.0
Requires-Dist: pymbend>=0.1.0
Requires-Dist: pyzstd>=0.16.1
Requires-Dist: rich>=13.7.1
Requires-Dist: scipy>=1.13.0
Requires-Dist: typer>=0.12.4
